test_pypi_anbltest/__init__.py
test_pypi_anbltest/__main__.py
test_pypi_anbltest/entry.py
cmdline_test_pypi_anbltest-0.1.3.dist-info/METADATA
cmdline_test_pypi_anbltest-0.1.3.dist-info/WHEEL
cmdline_test_pypi_anbltest-0.1.3.dist-info/entry_points.txt
cmdline_test_pypi_anbltest-0.1.3.dist-info/top_level.txt
cmdline_test_pypi_anbltest-0.1.3.dist-info/RECORD
