Metadata-Version: 2.1
Name: cmdline-test-pypi-anbltest
Version: 0.1.3
Summary: Python command line application bare bones template.
Home-page: http://gehrcke.de/2014/02/distributing-a-python-command-line-applicationqwqw
Author: Jan-Philip Gehrckeqqw
Author-email: jgehrckqwwqe@googlemail.com
License: UNKNOWN
Platform: UNKNOWN
